{
  "sport": {
    "sportId": "1429",
    "sportName": "Бильярд",
    "championships": [
      {
        "championshipId": "57510",
        "championshipName": "Снукер. Чемпионат мира. Шеффилд. Квалификация. Из 19 фреймов",
        "matches": [
          {
            "eventId": "54692188",
            "time": "2025-04-15 19:00:00",
            "team1": "Уилсон Гари",
            "team2": "Уэллс Д",
            "odds": {},
            "events": []
          },
          {
            "eventId": "54692291",
            "time": "2025-04-15 19:00:00",
            "team1": "Гилберт Д",
            "team2": "Хилл А",
            "odds": {},
            "events": []
          },
          {
            "eventId": "54702714",
            "time": "2025-04-16 13:00:00",
            "team1": "Селт М",
            "team2": "Робертсон Дж",
            "odds": {
              "1": 1.67,
              "2": 2.2,
              "HANDICAP 1": {
                "value": 1.98,
                "param": "-1.5"
              },
              "HANDICAP 2": {
                "value": 1.83,
                "param": "+1.5"
              },
              "TOTAL": "16.5",
              "OVER": 1.77,
              "UNDER": 2.05
            },
            "events": []
          },
          {
            "eventId": "54702729",
            "time": "2025-04-16 13:00:00",
            "team1": "Холт М",
            "team2": "Фань Чженгуи",
            "odds": {
              "1": 2.3,
              "2": 1.62,
              "HANDICAP 1": {
                "value": 1.9,
                "param": "+1.5"
              },
              "HANDICAP 2": {
                "value": 1.9,
                "param": "-1.5"
              },
              "TOTAL": "16.5",
              "OVER": 1.78,
              "UNDER": 2.04
            },
            "events": []
          },
          {
            "eventId": "54703055",
            "time": "2025-04-16 13:00:00",
            "team1": "Стивенс М",
            "team2": "У Йцзэ",
            "odds": {
              "1": 3.8,
              "2": 1.27,
              "HANDICAP 1": {
                "value": 1.77,
                "param": "+3.5"
              },
              "HANDICAP 2": {
                "value": 2.05,
                "param": "-3.5"
              },
              "TOTAL": "16.5",
              "OVER": 2.05,
              "UNDER": 1.77
            },
            "events": []
          },
          {
            "eventId": "54703057",
            "time": "2025-04-16 13:00:00",
            "team1": "Ян Гао",
            "team2": "Лэй Пэйфань",
            "odds": {
              "1": 2.6,
              "2": 1.5,
              "HANDICAP 1": {
                "value": 2.08,
                "param": "+1.5"
              },
              "HANDICAP 2": {
                "value": 1.75,
                "param": "-1.5"
              },
              "TOTAL": "16.5",
              "OVER": 1.83,
              "UNDER": 1.98
            },
            "events": []
          },
          {
            "eventId": "54703163",
            "time": "2025-04-16 13:00:00",
            "team1": "Ван Ю Чен",
            "team2": "Вафай Хуссейн",
            "odds": {
              "1": 4.1,
              "2": 1.24,
              "HANDICAP 1": {
                "value": 1.83,
                "param": "+3.5"
              },
              "HANDICAP 2": {
                "value": 1.98,
                "param": "-3.5"
              },
              "TOTAL": "16.5",
              "OVER": 2.12,
              "UNDER": 1.72
            },
            "events": []
          },
          {
            "eventId": "54703185",
            "time": "2025-04-16 13:00:00",
            "team1": "O'Коннор Дж",
            "team2": "Пэйдж Дж",
            "odds": {
              "1": 1.52,
              "2": 2.54,
              "HANDICAP 1": {
                "value": 1.78,
                "param": "-1.5"
              },
              "HANDICAP 2": {
                "value": 2.04,
                "param": "+1.5"
              },
              "TOTAL": "16.5",
              "OVER": 1.8,
              "UNDER": 2.0
            },
            "events": []
          },
          {
            "eventId": "54703189",
            "time": "2025-04-16 13:00:00",
            "team1": "Хэ Гоцян",
            "team2": "Картер А",
            "odds": {
              "1": 2.7,
              "2": 1.47,
              "HANDICAP 1": {
                "value": 1.77,
                "param": "+2.5"
              },
              "HANDICAP 2": {
                "value": 2.05,
                "param": "-2.5"
              },
              "TOTAL": "16.5",
              "OVER": 1.85,
              "UNDER": 1.95
            },
            "events": []
          },
          {
            "eventId": "54703191",
            "time": "2025-04-16 13:00:00",
            "team1": "Джонс Джейми",
            "team2": "Пан Джунсюй",
            "odds": {
              "1": 2.54,
              "2": 1.52,
              "HANDICAP 1": {
                "value": 2.05,
                "param": "+1.5"
              },
              "HANDICAP 2": {
                "value": 1.77,
                "param": "-1.5"
              },
              "TOTAL": "16.5",
              "OVER": 1.83,
              "UNDER": 1.98
            },
            "events": []
          }
        ]
      }
    ]
  }
}