{
  "sport": {
    "sportId": "1891",
    "sportName": "Велоспорт",
    "championships": [
      {
        "championshipId": "106162",
        "championshipName": "Джиро д’Абруццо. 2-й этап. Кто выше?",
        "matches": [
          {
            "eventId": "54720415",
            "time": "2025-04-16 12:50:00",
            "team1": "Кови А",
            "team2": "Марцелеллузи М",
            "odds": {},
            "events": []
          },
          {
            "eventId": "54720416",
            "time": "2025-04-16 12:50:00",
            "team1": "Хоусон Д",
            "team2": "Беннет Ж",
            "odds": {},
            "events": []
          },
          {
            "eventId": "54720417",
            "time": "2025-04-16 12:50:00",
            "team1": "Фанчеллу А",
            "team2": "Бреннер М",
            "odds": {},
            "events": []
          },
          {
            "eventId": "54720418",
            "time": "2025-04-16 12:50:00",
            "team1": "Ванхоук Х",
            "team2": "Мартин А",
            "odds": {},
            "events": []
          },
          {
            "eventId": "54720430",
            "time": "2025-04-16 12:50:00",
            "team1": "Палетти Л",
            "team2": "Зерай Н",
            "odds": {},
            "events": []
          },
          {
            "eventId": "54720449",
            "time": "2025-04-16 12:50:00",
            "team1": "Рондель М",
            "team2": "Мейнджес Л",
            "odds": {},
            "events": []
          },
          {
            "eventId": "54720450",
            "time": "2025-04-16 12:50:00",
            "team1": "Торрес П",
            "team2": "Де ла Круз Д",
            "odds": {},
            "events": []
          },
          {
            "eventId": "54720477",
            "time": "2025-04-16 12:50:00",
            "team1": "Раккани С",
            "team2": "Крешиоли Л",
            "odds": {},
            "events": []
          },
          {
            "eventId": "54720479",
            "time": "2025-04-16 12:50:00",
            "team1": "Конти В",
            "team2": "Зиммерманн Г",
            "odds": {},
            "events": []
          },
          {
            "eventId": "54720490",
            "time": "2025-04-16 12:50:00",
            "team1": "Фиорелли Ф",
            "team2": "Дати Т",
            "odds": {},
            "events": []
          }
        ]
      },
      {
        "championshipId": "123539",
        "championshipName": "Тур Лимбурга. Кто выше?",
        "matches": [
          {
            "eventId": "54720635",
            "time": "2025-04-16 14:00:00",
            "team1": "Гирмай Б",
            "team2": "Кубис Л",
            "odds": {},
            "events": []
          },
          {
            "eventId": "54720636",
            "time": "2025-04-16 14:00:00",
            "team1": "Тессон Дж",
            "team2": "Дюпонт Т",
            "odds": {},
            "events": []
          },
          {
            "eventId": "54720637",
            "time": "2025-04-16 14:00:00",
            "team1": "Галван Ф",
            "team2": "Дофин Ф",
            "odds": {},
            "events": []
          },
          {
            "eventId": "54720657",
            "time": "2025-04-16 14:00:00",
            "team1": "Брустенга М",
            "team2": "Перраччоне А",
            "odds": {},
            "events": []
          },
          {
            "eventId": "54720672",
            "time": "2025-04-16 14:00:00",
            "team1": "Москетти М",
            "team2": "Фретин М",
            "odds": {},
            "events": []
          },
          {
            "eventId": "54720673",
            "time": "2025-04-16 14:00:00",
            "team1": "Аниолковски С",
            "team2": "Ниццоло Ж",
            "odds": {},
            "events": []
          }
        ]
      }
    ]
  }
}